ExcelSage/ExcelSage.py
ExcelSage/__init__.py
robotframework_excelsage-1.2.0.dist-info/licenses/LICENSE
robotframework_excelsage-1.2.0.dist-info/METADATA
robotframework_excelsage-1.2.0.dist-info/WHEEL
robotframework_excelsage-1.2.0.dist-info/top_level.txt
robotframework_excelsage-1.2.0.dist-info/RECORD
