Metadata-Version: 2.4
Name: robotframework-excelsage
Version: 1.2.0
Summary: A package for integrating Robot Framework with Excel using openpyxl and pandas
Home-page: https://github.com/deekshith-poojary98/robotframework-excelsage
Author: Deekshith Poojary
Author-email: deekshithpoojary355@gmail.com
Maintainer: Deekshith Poojary
License: Apache License 2.0
Keywords: excel testing testautomation robotframework robotframework-excelsage robotframework-excellibrary robotframework-excellib
Classifier: Programming Language :: Python :: 3
Classifier: License :: OSI Approved :: Apache Software License
Classifier: Operating System :: OS Independent
Classifier: Framework :: Robot Framework :: Library
Classifier: Intended Audience :: Developers
Classifier: Topic :: Software Development :: Testing
Requires-Python: >=3.8
License-File: LICENSE
Requires-Dist: pyarrow
Requires-Dist: pandas>=2.2.0
Requires-Dist: openpyxl>=3.1.0
Requires-Dist: robotframework>=5.0.1
Dynamic: author
Dynamic: author-email
Dynamic: classifier
Dynamic: description
Dynamic: description-content-type
Dynamic: home-page
Dynamic: keywords
Dynamic: license
Dynamic: license-file
Dynamic: maintainer
Dynamic: requires-dist
Dynamic: requires-python
Dynamic: summary
